incerto/__init__.py
incerto/core.py
incerto-0.0.1.dist-info/licenses/LICENSE
incerto-0.0.1.dist-info/METADATA
incerto-0.0.1.dist-info/WHEEL
incerto-0.0.1.dist-info/top_level.txt
incerto-0.0.1.dist-info/RECORD
