Metadata-Version: 2.4
Name: incerto
Version: 0.0.1
Summary: A library for uncertainty quantification in machine learning
Author-email: Stephan Rabanser <stephan@cs.toronto.edu>
License: MIT
Requires-Python: >=3.10
License-File: LICENSE
Requires-Dist: matplotlib>=3.10.3
Requires-Dist: numpy>=2.2.5
Dynamic: license-file
